tidybear/__init__.py
tidybear/groupby.py
tidybear/selectors.py
tidybear/utils.py
tidybear/verbs/__init__.py
tidybear/verbs/count.py
tidybear/verbs/join.py
tidybear/verbs/mutate.py
tidybear/verbs/pivot.py
tidybear/verbs/rename.py
tidybear/verbs/select.py
tidybear/verbs/slice.py
tidybear-0.0.5.dist-info/LICENSE
tidybear-0.0.5.dist-info/METADATA
tidybear-0.0.5.dist-info/WHEEL
tidybear-0.0.5.dist-info/top_level.txt
tidybear-0.0.5.dist-info/RECORD
