Metadata-Version: 2.1
Name: tidybear
Version: 0.0.5
Summary: "A tidier approach to pandas."
Home-page: https://github.com/mbmackenzie/tidybear
Author: Matt Mackenzie
Author-email: mbm2228@columbia.edu
License: MIT
Platform: UNKNOWN
Classifier: License :: OSI Approved :: MIT License
Classifier: Programming Language :: Python :: 3
Classifier: Programming Language :: Python :: 3 :: Only
Classifier: Programming Language :: Python :: 3.8
Classifier: Programming Language :: Python :: 3.9
Classifier: Programming Language :: Python :: 3.10
Classifier: Programming Language :: Python :: Implementation :: CPython
Requires-Python: >=3.8
License-File: LICENSE
Requires-Dist: pandas
